polars_runtime_32-1.35.2.dist-info/METADATA
polars_runtime_32-1.35.2.dist-info/WHEEL
polars_runtime_32-1.35.2.dist-info/licenses/LICENSE
_polars_runtime_32/build_feature_flags.py
_polars_runtime_32/__init__.py
_polars_runtime_32/_polars_runtime_32.abi3.so
polars_runtime_32-1.35.2.dist-info/RECORD
