Metadata-Version: 2.4
Name: polars-runtime-32
Version: 1.35.2
Classifier: Development Status :: 5 - Production/Stable
Classifier: Environment :: Console
Classifier: Intended Audience :: Science/Research
Classifier: License :: OSI Approved :: MIT License
Classifier: Operating System :: OS Independent
Classifier: Programming Language :: Python
Classifier: Programming Language :: Python :: 3
Classifier: Programming Language :: Python :: 3 :: Only
Classifier: Programming Language :: Python :: 3.9
Classifier: Programming Language :: Python :: 3.10
Classifier: Programming Language :: Python :: 3.11
Classifier: Programming Language :: Python :: 3.12
Classifier: Programming Language :: Python :: 3.13
Classifier: Programming Language :: Rust
Classifier: Topic :: Scientific/Engineering
Classifier: Typing :: Typed
License-File: LICENSE
Summary: Blazingly fast DataFrame library
Keywords: dataframe,arrow,out-of-core
Author-email: Ritchie Vink <ritchie46@gmail.com>
Requires-Python: >=3.9
Project-URL: Homepage, https://www.pola.rs/
Project-URL: Documentation, https://docs.pola.rs/api/python/stable/reference/index.html
Project-URL: Repository, https://github.com/pola-rs/polars
Project-URL: Changelog, https://github.com/pola-rs/polars/releases
